scripts/validate_a2a_agent.py
scripts/validate_agent.py
servicenow_api/__init__.py
servicenow_api/__main__.py
servicenow_api/decorators.py
servicenow_api/exceptions.py
servicenow_api/mcp_config.json
servicenow_api/middlewares.py
servicenow_api/servicenow_agent.py
servicenow_api/servicenow_api.py
servicenow_api/servicenow_mcp.py
servicenow_api/servicenow_models.py
servicenow_api/utils.py
servicenow_api/skills/servicenow-account/SKILL.md
servicenow_api/skills/servicenow-activity-subscriptions/SKILL.md
servicenow_api/skills/servicenow-aggregate/SKILL.md
servicenow_api/skills/servicenow-application/SKILL.md
servicenow_api/skills/servicenow-attachment/SKILL.md
servicenow_api/skills/servicenow-auth/SKILL.md
servicenow_api/skills/servicenow-batch/SKILL.md
servicenow_api/skills/servicenow-change-management/SKILL.md
servicenow_api/skills/servicenow-cicd/SKILL.md
servicenow_api/skills/servicenow-cilifecycle/SKILL.md
servicenow_api/skills/servicenow-cmdb/SKILL.md
servicenow_api/skills/servicenow-custom-api/SKILL.md
servicenow_api/skills/servicenow-data-classification/SKILL.md
servicenow_api/skills/servicenow-devops/SKILL.md
servicenow_api/skills/servicenow-email/SKILL.md
servicenow_api/skills/servicenow-hr/SKILL.md
servicenow_api/skills/servicenow-import-sets/SKILL.md
servicenow_api/skills/servicenow-incidents/SKILL.md
servicenow_api/skills/servicenow-knowledge-management/SKILL.md
servicenow_api/skills/servicenow-metricbase/SKILL.md
servicenow_api/skills/servicenow-plugins/SKILL.md
servicenow_api/skills/servicenow-ppm/SKILL.md
servicenow_api/skills/servicenow-product-inventory/SKILL.md
servicenow_api/skills/servicenow-service-qualification/SKILL.md
servicenow_api/skills/servicenow-source-control/SKILL.md
servicenow_api/skills/servicenow-table-api/SKILL.md
servicenow_api/skills/servicenow-testing/SKILL.md
servicenow_api/skills/servicenow-update-sets/SKILL.md
servicenow_api-1.5.10.dist-info/licenses/LICENSE
tests/conftest.py
tests/test_change_requests.py
tests/test_incidents.py
tests/test_servicenow_api.py
servicenow_api-1.5.10.dist-info/METADATA
servicenow_api-1.5.10.dist-info/WHEEL
servicenow_api-1.5.10.dist-info/entry_points.txt
servicenow_api-1.5.10.dist-info/top_level.txt
servicenow_api-1.5.10.dist-info/RECORD
